<?xml version="1.0" encoding="utf-8" ?><dwsync><file name="AnonymousClass.class.php" server="osc.rtanewmedia.ca//OSC/" local="3544795227" remote="3542982060" Dst="-1" /><file name="Configurator.class.php" server="osc.rtanewmedia.ca//OSC/" local="3544795227" remote="3542982060" Dst="-1" /><file name="Controller.class.php" server="osc.rtanewmedia.ca//OSC/" local="3544795227" remote="3542982060" Dst="-1" /><file name="DBConnectionManager.class.php" server="osc.rtanewmedia.ca//OSC/" local="3544795227" remote="3542982060" Dst="-1" /><file name="Route.class.php" server="osc.rtanewmedia.ca//OSC/" local="3544795227" remote="3542982060" Dst="-1" /><file name="Router.class.php" server="osc.rtanewmedia.ca//OSC/" local="3544795227" remote="3542982060" Dst="-1" /><file name="VarTools.class.php" server="osc.rtanewmedia.ca//OSC/" local="3544795227" remote="3542982060" Dst="-1" /><file name="AnonymousClass.class.php" server="osc.rtanewmedia.ca//httpdocs/" local="3544795227" remote="3544799640" Dst="-1" /><file name="Configurator.class.php" server="osc.rtanewmedia.ca//httpdocs/" local="3544795227" remote="3544799640" Dst="-1" /><file name="Controller.class.php" server="osc.rtanewmedia.ca//httpdocs/" local="3544795227" remote="3544799640" Dst="-1" /><file name="DBConnectionManager.class.php" server="osc.rtanewmedia.ca//httpdocs/" local="3544795227" remote="3544799640" Dst="-1" /><file name="Route.class.php" server="osc.rtanewmedia.ca//httpdocs/" local="3544795227" remote="3544799640" Dst="-1" /><file name="Router.class.php" server="osc.rtanewmedia.ca//httpdocs/" local="3544795227" remote="3544799640" Dst="-1" /><file name="VarTools.class.php" server="osc.rtanewmedia.ca//httpdocs/" local="3544795227" remote="3544799640" Dst="-1" /></dwsync>