<?xml version="1.0" encoding="utf-8" ?><dwsync><file name="depth_1.png" server="osc.rtanewmedia.ca//httpdocs/" local="3548893832" remote="3548899380" Dst="-1" /><file name="depth_2.png" server="osc.rtanewmedia.ca//httpdocs/" local="3548893813" remote="3548899380" Dst="-1" /><file name="hum_1_1.png" server="osc.rtanewmedia.ca//httpdocs/" local="3548893795" remote="3548899380" Dst="-1" /><file name="hum_1_2.png" server="osc.rtanewmedia.ca//httpdocs/" local="3548893777" remote="3548899380" Dst="-1" /><file name="hum_1_3.png" server="osc.rtanewmedia.ca//httpdocs/" local="3548893759" remote="3548899380" Dst="-1" /><file name="hum_1_4.png" server="osc.rtanewmedia.ca//httpdocs/" local="3548893740" remote="3548899380" Dst="-1" /><file name="hum_2_1.png" server="osc.rtanewmedia.ca//httpdocs/" local="3548893722" remote="3548899380" Dst="-1" /><file name="hum_2_2.png" server="osc.rtanewmedia.ca//httpdocs/" local="3548893704" remote="3548899380" Dst="-1" /><file name="hum_2_3.png" server="osc.rtanewmedia.ca//httpdocs/" local="3548893684" remote="3548899380" Dst="-1" /><file name="hum_2_4.png" server="osc.rtanewmedia.ca//httpdocs/" local="3548893665" remote="3548899380" Dst="-1" /><file name="inn_1_1.png" server="osc.rtanewmedia.ca//httpdocs/" local="3548893646" remote="3548899380" Dst="-1" /><file name="inn_1_2.png" server="osc.rtanewmedia.ca//httpdocs/" local="3548893627" remote="3548899380" Dst="-1" /><file name="inn_1_3.png" server="osc.rtanewmedia.ca//httpdocs/" local="3548893608" remote="3548899380" Dst="-1" /><file name="inn_1_4.png" server="osc.rtanewmedia.ca//httpdocs/" local="3548893590" remote="3548899380" Dst="-1" /><file name="inn_2_1.png" server="osc.rtanewmedia.ca//httpdocs/" local="3548893571" remote="3548899380" Dst="-1" /><file name="inn_2_2.png" server="osc.rtanewmedia.ca//httpdocs/" local="3548893552" remote="3548899380" Dst="-1" /><file name="inn_2_3.png" server="osc.rtanewmedia.ca//httpdocs/" local="3548893534" remote="3548899380" Dst="-1" /><file name="inn_2_4.png" server="osc.rtanewmedia.ca//httpdocs/" local="3548893515" remote="3548899380" Dst="-1" /><file name="liv_1_1.png" server="osc.rtanewmedia.ca//httpdocs/" local="3548893497" remote="3548899380" Dst="-1" /><file name="liv_1_2.png" server="osc.rtanewmedia.ca//httpdocs/" local="3548893478" remote="3548899380" Dst="-1" /><file name="liv_1_3.png" server="osc.rtanewmedia.ca//httpdocs/" local="3548893459" remote="3548899380" Dst="-1" /><file name="liv_1_4.png" server="osc.rtanewmedia.ca//httpdocs/" local="3548893440" remote="3548899380" Dst="-1" /><file name="liv_2_1.png" server="osc.rtanewmedia.ca//httpdocs/" local="3548893421" remote="3548899380" Dst="-1" /><file name="liv_2_2.png" server="osc.rtanewmedia.ca//httpdocs/" local="3548893403" remote="3548899380" Dst="-1" /><file name="liv_2_3.png" server="osc.rtanewmedia.ca//httpdocs/" local="3548893385" remote="3548899380" Dst="-1" /><file name="liv_2_4.png" server="osc.rtanewmedia.ca//httpdocs/" local="3548893366" remote="3548899380" Dst="-1" /><file name="sci_1_1.png" server="osc.rtanewmedia.ca//httpdocs/" local="3548893348" remote="3548899380" Dst="-1" /><file name="sci_1_2.png" server="osc.rtanewmedia.ca//httpdocs/" local="3548893329" remote="3548899380" Dst="-1" /><file name="sci_1_3.png" server="osc.rtanewmedia.ca//httpdocs/" local="3548893310" remote="3548899380" Dst="-1" /><file name="sci_1_4.png" server="osc.rtanewmedia.ca//httpdocs/" local="3548893292" remote="3548899380" Dst="-1" /><file name="sci_2_1.png" server="osc.rtanewmedia.ca//httpdocs/" local="3548893273" remote="3548899380" Dst="-1" /><file name="sci_2_2.png" server="osc.rtanewmedia.ca//httpdocs/" local="3548893255" remote="3548899380" Dst="-1" /><file name="sci_2_3.png" server="osc.rtanewmedia.ca//httpdocs/" local="3548893236" remote="3548899380" Dst="-1" /><file name="sci_2_4.png" server="osc.rtanewmedia.ca//httpdocs/" local="3548893218" remote="3548899380" Dst="-1" /></dwsync>